{"highlevel": {"danceability": {"all": {"danceable": 0.525277495384,"not_danceable": 0.474722504616},"probability": 0.525277495384,"value": "danceable"},"gender": {"all": {"female": 0.0934297218919,"male": 0.906570255756},"probability": 0.906570255756,"value": "male"},"genre_dortmund": {"all": {"alternative": 0.12379834801,"blues": 0.0197753999382,"electronic": 0.811073362827,"folkcountry": 0.0118156308308,"funksoulrnb": 0.00181739788968,"jazz": 0.00332137220539,"pop": 0.00336100603454,"raphiphop": 0.00150594883598,"rock": 0.0235315207392},"probability": 0.811073362827,"value": "electronic"},"genre_electronic": {"all": {"ambient": 0.13644425571,"dnb": 0.0289193000644,"house": 0.0528771840036,"techno": 0.0152970980853,"trance": 0.766462147236},"probability": 0.766462147236,"value": "trance"},"genre_rosamerica": {"all": {"cla": 0.000123274498037,"dan": 0.0165917649865,"hip": 0.00277536199428,"jaz": 0.000759013346396,"pop": 0.041114654392,"rhy": 0.000424965372076,"roc": 0.937990307808,"spe": 0.000220665780944},"probability": 0.937990307808,"value": "roc"},"genre_tzanetakis": {"all": {"blu": 0.0626613423228,"cla": 0.0348169617355,"cou": 0.104475811124,"dis": 0.0784321576357,"hip": 0.15692435205,"jaz": 0.313974827528,"met": 0.0448166541755,"pop": 0.0627359300852,"reg": 0.0627360641956,"roc": 0.0784258767962},"probability": 0.313974827528,"value": "jaz"},"ismir04_rhythm": {"all": {"ChaChaCha": 0.22515425086,"Jive": 0.180220618844,"Quickstep": 0.0274204127491,"Rumba-American": 0.0692200660706,"Rumba-International": 0.0310022402555,"Rumba-Misc": 0.0228323712945,"Samba": 0.0630603507161,"Tango": 0.202788665891,"VienneseWaltz": 0.160788014531,"Waltz": 0.0175130181015},"probability": 0.22515425086,"value": "ChaChaCha"},"mood_acoustic": {"all": {"acoustic": 0.00368419941515,"not_acoustic": 0.996315777302},"probability": 0.996315777302,"value": "not_acoustic"},"mood_aggressive": {"all": {"aggressive": 0.969341397285,"not_aggressive": 0.030658621341},"probability": 0.969341397285,"value": "aggressive"},"mood_electronic": {"all": {"electronic": 0.318988323212,"not_electronic": 0.681011676788},"probability": 0.681011676788,"value": "not_electronic"},"mood_happy": {"all": {"happy": 0.321260243654,"not_happy": 0.678739726543},"probability": 0.678739726543,"value": "not_happy"},"mood_party": {"all": {"not_party": 0.387400835752,"party": 0.612599134445},"probability": 0.612599134445,"value": "party"},"mood_relaxed": {"all": {"not_relaxed": 0.954777479172,"relaxed": 0.0452225096524},"probability": 0.954777479172,"value": "not_relaxed"},"mood_sad": {"all": {"not_sad": 0.951503753662,"sad": 0.0484962686896},"probability": 0.951503753662,"value": "not_sad"},"moods_mirex": {"all": {"Cluster1": 0.0854099541903,"Cluster2": 0.0420683547854,"Cluster3": 0.0365821793675,"Cluster4": 0.0377120226622,"Cluster5": 0.798227488995},"probability": 0.798227488995,"value": "Cluster5"},"timbre": {"all": {"bright": 0.0164823848754,"dark": 0.983517587185},"probability": 0.983517587185,"value": "dark"},"tonal_atonal": {"all": {"atonal": 0.281181901693,"tonal": 0.718818128109},"probability": 0.718818128109,"value": "tonal"},"voice_instrumental": {"all": {"instrumental": 0.105730071664,"voice": 0.894269943237},"probability": 0.894269943237,"value": "voice"}},"metadata": {"audio_properties": {"analysis_sample_rate": 44100,"bit_rate": 0,"equal_loudness": 0,"length": 225.160003662,"lossless": 1,"replay_gain": -15.0580272675,"sample_rate": 44100,"codec": "flac","downmix": "mix","md5_encoded": "9a0690057354fe5f4bdcc4a3401e15c9"},"tags": {"file_name": "03 - Out of You.flac","acoustid_id": ["beb01d2b-4905-4841-b5ae-e901e47b9c0b"],"album": ["Fatal Design"],"albumartist": ["Entwine"],"albumartistsort": ["Entwine"],"artist": ["Entwine"],"artistsort": ["Entwine"],"asin": ["B000HIVRHK"],"barcode": ["0602498756003"],"catalognumber": ["Naula 076"],"date": ["2006-08-23"],"discnumber": ["1"],"disctotal": ["1"],"genre": ["Metal"],"grouping": ["Metal"],"label": ["Spikefarm Records"],"media": ["CD"],"mood": ["Melancholic"],"musicbrainz_albumartistid": ["eb2432e6-8d97-41b0-beba-b36e77ddc5b8"],"musicbrainz_albumid": ["f420a6cf-a98d-4803-b09e-7055586e634d"],"musicbrainz_artistid": ["eb2432e6-8d97-41b0-beba-b36e77ddc5b8"],"musicbrainz_recordingid": ["e75fdd19-3205-4193-9be7-501919176a84"],"musicbrainz_releasegroupid": ["dc87f27a-4699-3dc4-ae9e-3aaef26d7c4d"],"musicbrainz_releasetrackid": ["f3087ccd-6856-34ec-805c-481997afeed5"],"originaldate": ["2006-08-23"],"originalyear": ["2006"],"releasecountry": ["FI"],"releasestatus": ["official"],"releasetype": ["album"],"script": ["Latn"],"title": ["Out of You"],"totaldiscs": ["1"],"totaltracks": ["10"],"tracknumber": ["3"],"tracktotal": ["10"]},"version": {"highlevel": {"essentia": "2.1-beta5-dev","essentia_build_sha": "e74af04b57b164eed312abeef4963962215860f0","essentia_git_sha": "v2.1_beta4-499-g4013ebc","extractor": "music 2.0","gaia": "2.4.5","gaia_git_sha": "v2.4.4-44-g95f4851","models_essentia_git_sha": "v2.1_beta1"},"lowlevel": {"essentia": "2.1-beta2","essentia_build_sha": "2d9f1f26377add8aeb1075a9c2973f962c4f09fd","essentia_git_sha": "v2.1_beta2-1-ge3940c0","extractor": "music 1.0"}}}}