{"highlevel": {"danceability": {"all": {"danceable": 3.00000096379e-14,"not_danceable": 1},"probability": 1,"value": "not_danceable"},"gender": {"all": {"female": 0.537065684795,"male": 0.462934315205},"probability": 0.537065684795,"value": "female"},"genre_dortmund": {"all": {"alternative": 6.17424583682e-11,"blues": 6.20308041044e-11,"electronic": 0.999998986721,"folkcountry": 2.8648889483e-08,"funksoulrnb": 1.5848018009e-08,"jazz": 8.0510932321e-07,"pop": 2.10564721215e-08,"raphiphop": 2.1465320188e-08,"rock": 9.35691417681e-08},"probability": 0.999998986721,"value": "electronic"},"genre_electronic": {"all": {"ambient": 0.456224441528,"dnb": 0.0134490346536,"house": 0.338063061237,"techno": 0.11344332993,"trance": 0.0788201466203},"probability": 0.456224441528,"value": "ambient"},"genre_rosamerica": {"all": {"cla": 0.000990687054582,"dan": 0.0142869530246,"hip": 0.0369961299002,"jaz": 0.00819979328662,"pop": 0.0042694886215,"rhy": 0.932818174362,"roc": 0.000367951928638,"spe": 0.00207084277645},"probability": 0.932818174362,"value": "rhy"},"genre_tzanetakis": {"all": {"blu": 0.0454478003085,"cla": 0.121176205575,"cou": 0.0726853385568,"dis": 0.0726827085018,"hip": 0.051917526871,"jaz": 0.181718662381,"met": 0.0605817064643,"pop": 0.121165342629,"reg": 0.0908760130405,"roc": 0.181748703122},"probability": 0.181748703122,"value": "roc"},"ismir04_rhythm": {"all": {"ChaChaCha": 0.0172213297337,"Jive": 0.0237405057997,"Quickstep": 0.00279224570841,"Rumba-American": 0.0052780052647,"Rumba-International": 0.00605692761019,"Rumba-Misc": 0.0073094824329,"Samba": 0.0141507368535,"Tango": 0.915210008621,"VienneseWaltz": 0.00580979511142,"Waltz": 0.00243098870851},"probability": 0.915210008621,"value": "Tango"},"mood_acoustic": {"all": {"acoustic": 0.0951575860381,"not_acoustic": 0.904842436314},"probability": 0.904842436314,"value": "not_acoustic"},"mood_aggressive": {"all": {"aggressive": 3.00000096379e-14,"not_aggressive": 1},"probability": 1,"value": "not_aggressive"},"mood_electronic": {"all": {"electronic": 0.979391694069,"not_electronic": 0.0206082761288},"probability": 0.979391694069,"value": "electronic"},"mood_happy": {"all": {"happy": 0.010101784952,"not_happy": 0.989898204803},"probability": 0.989898204803,"value": "not_happy"},"mood_party": {"all": {"not_party": 0.999984204769,"party": 1.57784197654e-05},"probability": 0.999984204769,"value": "not_party"},"mood_relaxed": {"all": {"not_relaxed": 0.191182896495,"relaxed": 0.808817088604},"probability": 0.808817088604,"value": "relaxed"},"mood_sad": {"all": {"not_sad": 0.689952492714,"sad": 0.310047507286},"probability": 0.689952492714,"value": "not_sad"},"moods_mirex": {"all": {"Cluster1": 0.0813082307577,"Cluster2": 0.0482773147523,"Cluster3": 0.251114100218,"Cluster4": 0.0351580455899,"Cluster5": 0.584142327309},"probability": 0.584142327309,"value": "Cluster5"},"timbre": {"all": {"bright": 0.049348320812,"dark": 0.950651705265},"probability": 0.950651705265,"value": "dark"},"tonal_atonal": {"all": {"atonal": 1,"tonal": 1.06884327777e-10},"probability": 1,"value": "atonal"},"voice_instrumental": {"all": {"instrumental": 0.808663010597,"voice": 0.191336974502},"probability": 0.808663010597,"value": "instrumental"}},"metadata": {"audio_properties": {"analysis_sample_rate": 44100,"bit_rate": 0,"equal_loudness": 0,"length": 417.679992676,"lossless": 1,"replay_gain": -10.2545681,"sample_rate": 44100,"codec": "flac","downmix": "mix","md5_encoded": "6a267d07a13c3f73ff4fa977f50de59a"},"tags": {"file_name": "01 Der Traum Vom Fliegen.flac","album": ["Bionik"],"albumartist": ["Dominik Eulberg"],"albumartistsort": ["Eulberg, Dominik"],"artist": ["Dominik Eulberg"],"artistsort": ["Eulberg, Dominik"],"catalognumber": ["COR CD 015"],"date": ["2007-11-16"],"discnumber": ["1"],"disctotal": ["1"],"label": ["Cocoon Recordings"],"media": ["CD"],"musicbrainz_albumartistid": ["8f0d3885-04d9-4a13-aed7-96a25f9f9842"],"musicbrainz_albumid": ["85d1196a-3ab8-462f-8a4e-c3e7baab93c4"],"musicbrainz_artistid": ["8f0d3885-04d9-4a13-aed7-96a25f9f9842"],"musicbrainz_recordingid": ["25467245-4e4d-4db7-bf83-a9ba064431c5"],"musicbrainz_releasegroupid": ["9d4ec5dc-a663-3aea-8647-498d8f5c1393"],"originaldate": ["2007-11-16"],"releasecountry": ["DE"],"releasestatus": ["official"],"releasetype": ["album"],"script": ["Latn"],"title": ["Der Traum Vom Fliegen"],"totaldiscs": ["1"],"totaltracks": ["10"],"tracknumber": ["1"],"tracktotal": ["10"]},"version": {"highlevel": {"essentia": "2.1-beta5-dev","essentia_build_sha": "e74af04b57b164eed312abeef4963962215860f0","essentia_git_sha": "v2.1_beta4-499-g4013ebc","extractor": "music 2.0","gaia": "2.4.5","gaia_git_sha": "v2.4.4-44-g95f4851","models_essentia_git_sha": "v2.1_beta1"},"lowlevel": {"essentia": "2.1-beta2","essentia_build_sha": "70f2e5ece6736b2c40cc944ad0e695b16b925413","essentia_git_sha": "v2.1_beta2","extractor": "music 1.0"}}}}