{"highlevel": {"danceability": {"all": {"danceable": 0.216219127178,"not_danceable": 0.783780872822},"probability": 0.783780872822,"value": "not_danceable"},"gender": {"all": {"female": 0.0919366776943,"male": 0.908063352108},"probability": 0.908063352108,"value": "male"},"genre_dortmund": {"all": {"alternative": 0.0571590475738,"blues": 0.00756356306374,"electronic": 0.907851576805,"folkcountry": 0.010081156157,"funksoulrnb": 0.00108461303171,"jazz": 0.00146145164035,"pop": 0.00171411526389,"raphiphop": 0.000845375529025,"rock": 0.0122390715405},"probability": 0.907851576805,"value": "electronic"},"genre_electronic": {"all": {"ambient": 0.495219528675,"dnb": 0.0352469757199,"house": 0.0656844228506,"techno": 0.0166359990835,"trance": 0.387213081121},"probability": 0.495219528675,"value": "ambient"},"genre_rosamerica": {"all": {"cla": 0.0130527308211,"dan": 0.00647976715118,"hip": 0.00746497511864,"jaz": 0.00272556883283,"pop": 0.0567713864148,"rhy": 0.041164457798,"roc": 0.871575832367,"spe": 0.000765264849178},"probability": 0.871575832367,"value": "roc"},"genre_tzanetakis": {"all": {"blu": 0.0626613423228,"cla": 0.0348169617355,"cou": 0.104475811124,"dis": 0.0784321576357,"hip": 0.15692435205,"jaz": 0.313974827528,"met": 0.0448166541755,"pop": 0.0627359300852,"reg": 0.0627360641956,"roc": 0.0784258767962},"probability": 0.313974827528,"value": "jaz"},"ismir04_rhythm": {"all": {"ChaChaCha": 0.46744042635,"Jive": 0.130023419857,"Quickstep": 0.022215327248,"Rumba-American": 0.0430375188589,"Rumba-International": 0.0242221113294,"Rumba-Misc": 0.0190073233098,"Samba": 0.044376693666,"Tango": 0.114138543606,"VienneseWaltz": 0.119329355657,"Waltz": 0.0162092950195},"probability": 0.46744042635,"value": "ChaChaCha"},"mood_acoustic": {"all": {"acoustic": 0.007698004134,"not_acoustic": 0.992302000523},"probability": 0.992302000523,"value": "not_acoustic"},"mood_aggressive": {"all": {"aggressive": 0.420743644238,"not_aggressive": 0.579256355762},"probability": 0.579256355762,"value": "not_aggressive"},"mood_electronic": {"all": {"electronic": 0.475850611925,"not_electronic": 0.524149358273},"probability": 0.524149358273,"value": "not_electronic"},"mood_happy": {"all": {"happy": 0.578348994255,"not_happy": 0.421651005745},"probability": 0.578348994255,"value": "happy"},"mood_party": {"all": {"not_party": 0.368622988462,"party": 0.631376981735},"probability": 0.631376981735,"value": "party"},"mood_relaxed": {"all": {"not_relaxed": 0.694835603237,"relaxed": 0.305164366961},"probability": 0.694835603237,"value": "not_relaxed"},"mood_sad": {"all": {"not_sad": 0.868320763111,"sad": 0.131679221988},"probability": 0.868320763111,"value": "not_sad"},"moods_mirex": {"all": {"Cluster1": 0.0825716480613,"Cluster2": 0.114690110087,"Cluster3": 0.0498910695314,"Cluster4": 0.0651687681675,"Cluster5": 0.687678396702},"probability": 0.687678396702,"value": "Cluster5"},"timbre": {"all": {"bright": 0.164055451751,"dark": 0.835944533348},"probability": 0.835944533348,"value": "dark"},"tonal_atonal": {"all": {"atonal": 0.856179952621,"tonal": 0.143820077181},"probability": 0.856179952621,"value": "atonal"},"voice_instrumental": {"all": {"instrumental": 0.597871899605,"voice": 0.402128130198},"probability": 0.597871899605,"value": "instrumental"}},"metadata": {"audio_properties": {"analysis_sample_rate": 44100,"bit_rate": 0,"equal_loudness": 0,"length": 265.359985352,"lossless": 1,"replay_gain": -10.2558631897,"sample_rate": 44100,"codec": "flac","downmix": "mix","md5_encoded": "c9e0552efd472cd8871c2025b75ea3b8"},"tags": {"file_name": "09 Cajun Panther.flac","acoustid_id": ["638ab465-57d9-438b-85b4-847a900acbe3"],"album": ["Little Caesar"],"albumartist": ["Little Caesar"],"albumartistsort": ["Little Caesar"],"artist": ["Little Caesar"],"artistsort": ["Little Caesar"],"asin": ["B0000071MQ"],"barcode": ["075992428828"],"catalognumber": ["9 24288-D2"],"date": ["1990"],"discnumber": ["1"],"disctotal": ["1"],"genre": ["Hard Rock"],"grouping": ["Hard Rock"],"label": ["DGC Records"],"media": ["CD"],"mood": ["Unknown"],"musicbrainz_albumartistid": ["1288df18-90ac-4688-9700-b82a0abe7b7c"],"musicbrainz_albumid": ["86be6c84-ebf3-4b20-95ee-dc405671e0f3"],"musicbrainz_artistid": ["1288df18-90ac-4688-9700-b82a0abe7b7c"],"musicbrainz_recordingid": ["d6799fc7-0229-461d-bac8-9039cca4790c"],"musicbrainz_releasegroupid": ["f0f5d697-ade4-3e31-bc32-0143b3a59789"],"musicbrainz_releasetrackid": ["126a30f9-ef21-3aec-ae78-770a4b3615ce"],"originaldate": ["1990"],"originalyear": ["1990"],"releasecountry": ["US"],"releasestatus": ["official"],"releasetype": ["album"],"script": ["Latn"],"title": ["Cajun Panther"],"totaldiscs": ["1"],"totaltracks": ["12"],"tracknumber": ["9"],"tracktotal": ["12"],"website": ["http:\/\/www.littlecaesar.net\/"]},"version": {"highlevel": {"essentia": "2.1-beta5-dev","essentia_build_sha": "e74af04b57b164eed312abeef4963962215860f0","essentia_git_sha": "v2.1_beta4-499-g4013ebc","extractor": "music 2.0","gaia": "2.4.5","gaia_git_sha": "v2.4.4-44-g95f4851","models_essentia_git_sha": "v2.1_beta1"},"lowlevel": {"essentia": "2.1-beta2","essentia_build_sha": "70f2e5ece6736b2c40cc944ad0e695b16b925413","essentia_git_sha": "v2.1_beta2","extractor": "music 1.0"}}}}