{"highlevel": {"danceability": {"all": {"danceable": 0.484018683434,"not_danceable": 0.515981316566},"probability": 0.515981316566,"value": "not_danceable"},"gender": {"all": {"female": 0.625745236874,"male": 0.374254733324},"probability": 0.625745236874,"value": "female"},"genre_dortmund": {"all": {"alternative": 0.0205305274576,"blues": 0.00251592881978,"electronic": 0.964893460274,"folkcountry": 0.00316644948907,"funksoulrnb": 0.000121239616419,"jazz": 0.0067179123871,"pop": 0.000423803197918,"raphiphop": 9.90472181002e-05,"rock": 0.0015316096833},"probability": 0.964893460274,"value": "electronic"},"genre_electronic": {"all": {"ambient": 0.943625509739,"dnb": 0.00138818332925,"house": 0.0304001308978,"techno": 0.0199151765555,"trance": 0.00467100320384},"probability": 0.943625509739,"value": "ambient"},"genre_rosamerica": {"all": {"cla": 0.0531042069197,"dan": 0.00773611199111,"hip": 0.0616245009005,"jaz": 0.430215001106,"pop": 0.0394786968827,"rhy": 0.369249165058,"roc": 0.0106943463907,"spe": 0.0278979707509},"probability": 0.430215001106,"value": "jaz"},"genre_tzanetakis": {"all": {"blu": 0.0778564289212,"cla": 0.0345945470035,"cou": 0.104285053909,"dis": 0.0529825203121,"hip": 0.155808269978,"jaz": 0.311814188957,"met": 0.044524628669,"pop": 0.0779079794884,"reg": 0.0623231232166,"roc": 0.0779032558203},"probability": 0.311814188957,"value": "jaz"},"ismir04_rhythm": {"all": {"ChaChaCha": 0.0232214778662,"Jive": 0.00469210371375,"Quickstep": 0.00327098974958,"Rumba-American": 0.0155366715044,"Rumba-International": 0.0867502391338,"Rumba-Misc": 0.0250043068081,"Samba": 0.0105152726173,"Tango": 0.0863418281078,"VienneseWaltz": 0.731174111366,"Waltz": 0.0134929968044},"probability": 0.731174111366,"value": "VienneseWaltz"},"mood_acoustic": {"all": {"acoustic": 0.612664997578,"not_acoustic": 0.387335002422},"probability": 0.612664997578,"value": "acoustic"},"mood_aggressive": {"all": {"aggressive": 0.0273531395942,"not_aggressive": 0.972646832466},"probability": 0.972646832466,"value": "not_aggressive"},"mood_electronic": {"all": {"electronic": 0.73158711195,"not_electronic": 0.26841288805},"probability": 0.73158711195,"value": "electronic"},"mood_happy": {"all": {"happy": 8.39675351472e-09,"not_happy": 1},"probability": 1,"value": "not_happy"},"mood_party": {"all": {"not_party": 0.972192823887,"party": 0.0278071761131},"probability": 0.972192823887,"value": "not_party"},"mood_relaxed": {"all": {"not_relaxed": 0.0251107811928,"relaxed": 0.974889218807},"probability": 0.974889218807,"value": "relaxed"},"mood_sad": {"all": {"not_sad": 0.30013820529,"sad": 0.699861824512},"probability": 0.699861824512,"value": "sad"},"moods_mirex": {"all": {"Cluster1": 0.0903048962355,"Cluster2": 0.139682680368,"Cluster3": 0.583636879921,"Cluster4": 0.066803663969,"Cluster5": 0.119571901858},"probability": 0.583636879921,"value": "Cluster3"},"timbre": {"all": {"bright": 0.00350471539423,"dark": 0.996495306492},"probability": 0.996495306492,"value": "dark"},"tonal_atonal": {"all": {"atonal": 0.987758040428,"tonal": 0.0122419334948},"probability": 0.987758040428,"value": "atonal"},"voice_instrumental": {"all": {"instrumental": 0.98283046484,"voice": 0.0171695444733},"probability": 0.98283046484,"value": "instrumental"}},"metadata": {"audio_properties": {"analysis_sample_rate": 44100,"bit_rate": 0,"equal_loudness": 0,"length": 331.053344727,"lossless": 1,"replay_gain": -9.85017967224,"sample_rate": 44100,"codec": "flac","downmix": "mix","md5_encoded": "52f585a65ad38d81500e3a4dfb9d2f9c"},"tags": {"file_name": "04. Unkerich.flac","acoustid_id": ["d31ee9e5-50b2-46ae-ae5a-24a10d27ddd1"],"album": ["Dolores"],"albumartist": ["Bohren & der Club of Gore"],"albumartistsort": ["Bohren & der Club of Gore"],"artist": ["Bohren & der Club of Gore"],"artistsort": ["Bohren & der Club of Gore"],"asin": ["B001FWRYU6"],"catalognumber": ["IPC-108"],"date": ["2008-10-21"],"discnumber": ["1"],"disctotal": ["1"],"genre": ["Dark Ambient"],"label": ["Ipecac Recordings"],"media": ["CD"],"musicbrainz_albumartistid": ["938df0a0-c650-4cf8-9b23-5ad8a5cb4805"],"musicbrainz_albumid": ["73c90c4a-03de-4ea4-9057-41862e170b23"],"musicbrainz_artistid": ["938df0a0-c650-4cf8-9b23-5ad8a5cb4805"],"musicbrainz_recordingid": ["375b6ae8-babb-4ca8-bc29-1003ed760e7d"],"musicbrainz_releasegroupid": ["34bc24c4-e2b9-33ba-a18b-d8f2f3f14ca4"],"originaldate": ["2008-10-10"],"releasecountry": ["US"],"releasestatus": ["official"],"releasetype": ["album"],"script": ["Latn"],"title": ["Unkerich"],"totaldiscs": ["1"],"totaltracks": ["10"],"tracknumber": ["4"],"tracktotal": ["10"]},"version": {"highlevel": {"essentia": "2.1-beta5-dev","essentia_build_sha": "e74af04b57b164eed312abeef4963962215860f0","essentia_git_sha": "v2.1_beta4-499-g4013ebc","extractor": "music 2.0","gaia": "2.4.5","gaia_git_sha": "v2.4.4-44-g95f4851","models_essentia_git_sha": "v2.1_beta1"},"lowlevel": {"essentia": "2.1-beta2","essentia_build_sha": "70f2e5ece6736b2c40cc944ad0e695b16b925413","essentia_git_sha": "v2.1_beta2","extractor": "music 1.0"}}}}