{"highlevel": {"danceability": {"all": {"danceable": 0.511557579041,"not_danceable": 0.488442391157},"probability": 0.511557579041,"value": "danceable"},"gender": {"all": {"female": 0.15446986258,"male": 0.845530152321},"probability": 0.845530152321,"value": "male"},"genre_dortmund": {"all": {"alternative": 0.0926669761539,"blues": 0.0153429722413,"electronic": 0.849554955959,"folkcountry": 0.00980469398201,"funksoulrnb": 0.00170000630897,"jazz": 0.00367504917085,"pop": 0.00273694912903,"raphiphop": 0.00134026329033,"rock": 0.0231781490147},"probability": 0.849554955959,"value": "electronic"},"genre_electronic": {"all": {"ambient": 0.157350212336,"dnb": 0.0366169475019,"house": 0.04392240569,"techno": 0.0119851808995,"trance": 0.750125229359},"probability": 0.750125229359,"value": "trance"},"genre_rosamerica": {"all": {"cla": 0.0020460144151,"dan": 0.0292093995959,"hip": 0.00821559969336,"jaz": 0.00223443261348,"pop": 0.0344228856266,"rhy": 0.00171117961872,"roc": 0.91879850626,"spe": 0.00336196389981},"probability": 0.91879850626,"value": "roc"},"genre_tzanetakis": {"all": {"blu": 0.0626613423228,"cla": 0.0348169617355,"cou": 0.104475811124,"dis": 0.0784321576357,"hip": 0.15692435205,"jaz": 0.313974827528,"met": 0.0448166541755,"pop": 0.0627359300852,"reg": 0.0627360641956,"roc": 0.0784258767962},"probability": 0.313974827528,"value": "jaz"},"ismir04_rhythm": {"all": {"ChaChaCha": 0.453819900751,"Jive": 0.112823545933,"Quickstep": 0.0198804140091,"Rumba-American": 0.0228024628013,"Rumba-International": 0.0160626340657,"Rumba-Misc": 0.0145627893507,"Samba": 0.0530878044665,"Tango": 0.183889061213,"VienneseWaltz": 0.112122476101,"Waltz": 0.010948907584},"probability": 0.453819900751,"value": "ChaChaCha"},"mood_acoustic": {"all": {"acoustic": 0.00316398311406,"not_acoustic": 0.996836006641},"probability": 0.996836006641,"value": "not_acoustic"},"mood_aggressive": {"all": {"aggressive": 0.99256426096,"not_aggressive": 0.00743576372042},"probability": 0.99256426096,"value": "aggressive"},"mood_electronic": {"all": {"electronic": 0.290085583925,"not_electronic": 0.709914386272},"probability": 0.709914386272,"value": "not_electronic"},"mood_happy": {"all": {"happy": 0.0792957916856,"not_happy": 0.920704185963},"probability": 0.920704185963,"value": "not_happy"},"mood_party": {"all": {"not_party": 0.317209601402,"party": 0.682790398598},"probability": 0.682790398598,"value": "party"},"mood_relaxed": {"all": {"not_relaxed": 0.92497330904,"relaxed": 0.0750267058611},"probability": 0.92497330904,"value": "not_relaxed"},"mood_sad": {"all": {"not_sad": 0.970648825169,"sad": 0.0293511468917},"probability": 0.970648825169,"value": "not_sad"},"moods_mirex": {"all": {"Cluster1": 0.105141185224,"Cluster2": 0.0497436746955,"Cluster3": 0.0382943898439,"Cluster4": 0.0491280071437,"Cluster5": 0.757692754269},"probability": 0.757692754269,"value": "Cluster5"},"timbre": {"all": {"bright": 0.0380259677768,"dark": 0.961974024773},"probability": 0.961974024773,"value": "dark"},"tonal_atonal": {"all": {"atonal": 0.342046916485,"tonal": 0.657953083515},"probability": 0.657953083515,"value": "tonal"},"voice_instrumental": {"all": {"instrumental": 0.0429200194776,"voice": 0.957080006599},"probability": 0.957080006599,"value": "voice"}},"metadata": {"audio_properties": {"analysis_sample_rate": 44100,"bit_rate": 320000,"equal_loudness": 0,"length": 237.844894409,"lossless": 0,"replay_gain": -15.6381254196,"sample_rate": 44100,"codec": "mp3","downmix": "mix","md5_encoded": "7f285a711c7dbbe38208c35f003ed701"},"tags": {"file_name": "08 - S.O.S..mp3","album": ["Internal Revolution"],"albumartist": ["Diecast"],"albumartistsort": ["Diecast"],"artist": ["Diecast"],"artistsort": ["Diecast"],"asin": ["B000H0MMFO"],"barcode": ["727701832920"],"catalognumber": ["8329-2"],"contentgroup": ["Hardcore"],"date": ["2006-09-19"],"discnumber": ["1\/1"],"genre": ["Metal", "Hardcore", "Thrash Metal"],"label": ["Century Media"],"media": ["CD"],"mood": ["Unknown"],"musicbrainz album release country": ["US"],"musicbrainz album status": ["official"],"musicbrainz album type": ["album"],"musicbrainz_albumartistid": ["24282e0e-08ed-4181-8ff4-025270e84404"],"musicbrainz_albumid": ["13928c41-8fcd-4db1-a894-a26843a81797"],"musicbrainz_artistid": ["24282e0e-08ed-4181-8ff4-025270e84404"],"musicbrainz_recordingid": ["51cd8b89-51e2-4ad8-add0-4af272ac1e42"],"musicbrainz_releasegroupid": ["96314ce9-1f16-3ea4-b445-7e9dcd69aab8"],"originaldate": ["2006-09-19"],"originalyear": ["2006"],"script": ["Latn"],"title": ["S.O.S."],"tracknumber": ["8\/11"]},"version": {"highlevel": {"essentia": "2.1-beta5-dev","essentia_build_sha": "e74af04b57b164eed312abeef4963962215860f0","essentia_git_sha": "v2.1_beta4-499-g4013ebc","extractor": "music 2.0","gaia": "2.4.5","gaia_git_sha": "v2.4.4-44-g95f4851","models_essentia_git_sha": "v2.1_beta1"},"lowlevel": {"essentia": "2.1-beta2","essentia_build_sha": "70f2e5ece6736b2c40cc944ad0e695b16b925413","essentia_git_sha": "v2.1_beta2","extractor": "music 1.0"}}}}