{"highlevel": {"danceability": {"all": {"danceable": 3.00000096379e-14,"not_danceable": 1},"probability": 1,"value": "not_danceable"},"gender": {"all": {"female": 0.622126698494,"male": 0.377873301506},"probability": 0.622126698494,"value": "female"},"genre_dortmund": {"all": {"alternative": 1.01079666859e-09,"blues": 1.04628228303e-09,"electronic": 0.999996960163,"folkcountry": 2.66627807832e-07,"funksoulrnb": 4.60053541929e-08,"jazz": 2.49478262049e-06,"pop": 3.26709610476e-08,"raphiphop": 1.67598788181e-08,"rock": 1.76467054303e-07},"probability": 0.999996960163,"value": "electronic"},"genre_electronic": {"all": {"ambient": 0.407470583916,"dnb": 0.0062762494199,"house": 0.187917023897,"techno": 0.108612887561,"trance": 0.289723277092},"probability": 0.407470583916,"value": "ambient"},"genre_rosamerica": {"all": {"cla": 0.0110134333372,"dan": 0.0208931975067,"hip": 0.176712706685,"jaz": 0.194991156459,"pop": 0.130845397711,"rhy": 0.405073344707,"roc": 0.0309468377382,"spe": 0.0295239482075},"probability": 0.405073344707,"value": "rhy"},"genre_tzanetakis": {"all": {"blu": 0.0617713928223,"cla": 0.0343018434942,"cou": 0.102904699743,"dis": 0.0514719486237,"hip": 0.154438391328,"jaz": 0.309046447277,"met": 0.0441263727844,"pop": 0.0772129744291,"reg": 0.0617708563805,"roc": 0.102955065668},"probability": 0.309046447277,"value": "jaz"},"ismir04_rhythm": {"all": {"ChaChaCha": 0.10893625021,"Jive": 0.0974439457059,"Quickstep": 0.0311257448047,"Rumba-American": 0.0757991224527,"Rumba-International": 0.0480269752443,"Rumba-Misc": 0.0458296351135,"Samba": 0.159909024835,"Tango": 0.238462582231,"VienneseWaltz": 0.169007003307,"Waltz": 0.025459703058},"probability": 0.238462582231,"value": "Tango"},"mood_acoustic": {"all": {"acoustic": 0.0955901220441,"not_acoustic": 0.904409885406},"probability": 0.904409885406,"value": "not_acoustic"},"mood_aggressive": {"all": {"aggressive": 3.00000096379e-14,"not_aggressive": 1},"probability": 1,"value": "not_aggressive"},"mood_electronic": {"all": {"electronic": 0.979391694069,"not_electronic": 0.0206082761288},"probability": 0.979391694069,"value": "electronic"},"mood_happy": {"all": {"happy": 0.034956369549,"not_happy": 0.965043604374},"probability": 0.965043604374,"value": "not_happy"},"mood_party": {"all": {"not_party": 0.999984204769,"party": 1.57784197654e-05},"probability": 0.999984204769,"value": "not_party"},"mood_relaxed": {"all": {"not_relaxed": 0.191182896495,"relaxed": 0.808817088604},"probability": 0.808817088604,"value": "relaxed"},"mood_sad": {"all": {"not_sad": 0.727682828903,"sad": 0.272317200899},"probability": 0.727682828903,"value": "not_sad"},"moods_mirex": {"all": {"Cluster1": 0.0772180780768,"Cluster2": 0.0444045588374,"Cluster3": 0.22774425149,"Cluster4": 0.0306338258088,"Cluster5": 0.619999289513},"probability": 0.619999289513,"value": "Cluster5"},"timbre": {"all": {"bright": 0.00111519393977,"dark": 0.998884797096},"probability": 0.998884797096,"value": "dark"},"tonal_atonal": {"all": {"atonal": 0.999999344349,"tonal": 6.49833054922e-07},"probability": 0.999999344349,"value": "atonal"},"voice_instrumental": {"all": {"instrumental": 0.999996066093,"voice": 3.91608591599e-06},"probability": 0.999996066093,"value": "instrumental"}},"metadata": {"audio_properties": {"analysis_sample_rate": 44100,"bit_rate": 248835,"equal_loudness": 0,"length": 299.050872803,"lossless": 0,"replay_gain": -9.64646339417,"sample_rate": 44100,"codec": "mp3","downmix": "mix","md5_encoded": "d2bcfeba00851cfa3c9c73de52ef1903"},"tags": {"file_name": "11 I Don't Mind.mp3","album": ["SuperHeavy"],"album artist credit": ["SuperHeavy"],"albumartist": ["SuperHeavy"],"albumartistsort": ["SuperHeavy"],"artist": ["SuperHeavy"],"artist credit": ["SuperHeavy"],"artistsort": ["SuperHeavy"],"asin": ["B005HI7MZG"],"bpm": ["0"],"catalognumber": ["B0016106-02"],"date": ["2011"],"discnumber": ["1\/1"],"genre": ["Rock"],"label": ["Universal Republic Records"],"language": ["eng"],"media": ["CD"],"musicbrainz album release country": ["US"],"musicbrainz album status": ["official"],"musicbrainz album type": ["album"],"musicbrainz_albumartistid": ["7c891f6b-1abd-4b35-bb48-b163bdbf9c0e"],"musicbrainz_albumid": ["b33cdd0c-9743-4ed5-a36c-8523607e50e2"],"musicbrainz_artistid": ["7c891f6b-1abd-4b35-bb48-b163bdbf9c0e"],"musicbrainz_recordingid": ["3e6545d1-2e0d-42ca-be57-c755cd22effd"],"musicbrainz_releasegroupid": ["3d8c0c5e-b973-4987-88c0-c9fddc2b3af3"],"originaldate": ["2011"],"script": ["Latn", "Latn"],"title": ["I Don't Mind"],"tracknumber": ["11\/16"]},"version": {"highlevel": {"essentia": "2.1-beta5-dev","essentia_build_sha": "e74af04b57b164eed312abeef4963962215860f0","essentia_git_sha": "v2.1_beta4-499-g4013ebc","extractor": "music 2.0","gaia": "2.4.5","gaia_git_sha": "v2.4.4-44-g95f4851","models_essentia_git_sha": "v2.1_beta1"},"lowlevel": {"essentia": "2.1-beta1","essentia_build_sha": "9f04d4dd351e2d05498f0c7e4880499648f24ac0","essentia_git_sha": "v2.1_beta1-34-gf95df8b","extractor": "music 1.0"}}}}