{"highlevel": {"danceability": {"all": {"danceable": 0.229457378387,"not_danceable": 0.770542621613},"probability": 0.770542621613,"value": "not_danceable"},"gender": {"all": {"female": 0.294930547476,"male": 0.705069482327},"probability": 0.705069482327,"value": "male"},"genre_dortmund": {"all": {"alternative": 0.0450181737542,"blues": 0.552104055882,"electronic": 0.25672775507,"folkcountry": 0.0459069907665,"funksoulrnb": 0.00630464963615,"jazz": 0.0452045947313,"pop": 0.0059280465357,"raphiphop": 0.00297182658687,"rock": 0.0398338772357},"probability": 0.552104055882,"value": "blues"},"genre_electronic": {"all": {"ambient": 0.852725327015,"dnb": 0.0193319264799,"house": 0.09814106673,"techno": 0.0138384820893,"trance": 0.0159631967545},"probability": 0.852725327015,"value": "ambient"},"genre_rosamerica": {"all": {"cla": 0.856117844582,"dan": 0.00458525586873,"hip": 0.02481225878,"jaz": 0.0625183060765,"pop": 0.0114829670638,"rhy": 0.0187536329031,"roc": 0.00728836748749,"spe": 0.0144413411617},"probability": 0.856117844582,"value": "cla"},"genre_tzanetakis": {"all": {"blu": 0.00799269881099,"cla": 0.00240925769322,"cou": 0.00649659521878,"dis": 0.00525517622009,"hip": 0.848023056984,"jaz": 0.110587328672,"met": 0.00281647499651,"pop": 0.00513507984579,"reg": 0.00773996068165,"roc": 0.00354439369403},"probability": 0.848023056984,"value": "hip"},"ismir04_rhythm": {"all": {"ChaChaCha": 0.0102550648153,"Jive": 0.012054967694,"Quickstep": 0.00102751236409,"Rumba-American": 0.00140752783045,"Rumba-International": 0.000327241868945,"Rumba-Misc": 0.000356702570571,"Samba": 0.00265022227541,"Tango": 0.965789020061,"VienneseWaltz": 0.00515608349815,"Waltz": 0.000975668313913},"probability": 0.965789020061,"value": "Tango"},"mood_acoustic": {"all": {"acoustic": 0.122733026743,"not_acoustic": 0.877266943455},"probability": 0.877266943455,"value": "not_acoustic"},"mood_aggressive": {"all": {"aggressive": 0.0644389092922,"not_aggressive": 0.93556112051},"probability": 0.93556112051,"value": "not_aggressive"},"mood_electronic": {"all": {"electronic": 0.799182355404,"not_electronic": 0.200817644596},"probability": 0.799182355404,"value": "electronic"},"mood_happy": {"all": {"happy": 0.796090006828,"not_happy": 0.203909963369},"probability": 0.796090006828,"value": "happy"},"mood_party": {"all": {"not_party": 0.570012927055,"party": 0.429987043142},"probability": 0.570012927055,"value": "not_party"},"mood_relaxed": {"all": {"not_relaxed": 0.733505129814,"relaxed": 0.266494899988},"probability": 0.733505129814,"value": "not_relaxed"},"mood_sad": {"all": {"not_sad": 0.607543885708,"sad": 0.392456114292},"probability": 0.607543885708,"value": "not_sad"},"moods_mirex": {"all": {"Cluster1": 0.108774803579,"Cluster2": 0.24635951221,"Cluster3": 0.0502128899097,"Cluster4": 0.2409273386,"Cluster5": 0.353725463152},"probability": 0.353725463152,"value": "Cluster5"},"timbre": {"all": {"bright": 0.958571732044,"dark": 0.0414282605052},"probability": 0.958571732044,"value": "bright"},"tonal_atonal": {"all": {"atonal": 0.999985158443,"tonal": 1.4863967408e-05},"probability": 0.999985158443,"value": "atonal"},"voice_instrumental": {"all": {"instrumental": 0.999997913837,"voice": 2.10399821299e-06},"probability": 0.999997913837,"value": "instrumental"}},"metadata": {"audio_properties": {"analysis_sample_rate": 44100,"bit_rate": 0,"equal_loudness": 0,"length": 151.266662598,"lossless": 1,"replay_gain": -8.45433235168,"sample_rate": 44100,"codec": "flac","downmix": "mix","md5_encoded": "44e4a58d2656bca170621dc08d2b5f7c"},"tags": {"file_name": "1-19 War Dance for Wooden Indians.flac","acoustid_id": ["2383725a-a875-4d6e-870f-8c4ef057003f"],"album": ["Reckless Nights and Turkish Twilights"],"albumartist": ["Raymond Scott"],"albumartistsort": ["Scott, Raymond"],"artist": ["Raymond Scott"],"artistsort": ["Scott, Raymond"],"asin": ["B0012GMZ2M"],"barcode": ["074645302829"],"catalognumber": ["CK 53028"],"compilation": ["1"],"date": ["1992-10-27"],"discnumber": ["1"],"disctotal": ["1"],"genre": ["Swing"],"grouping": ["Jazz"],"label": ["Columbia"],"language": ["eng"],"media": ["CD"],"musicbrainz_albumartistid": ["1807480c-c81e-401a-8016-300758f51008"],"musicbrainz_albumid": ["7f1020f4-9089-4693-a9cc-e802472029a4"],"musicbrainz_artistid": ["1807480c-c81e-401a-8016-300758f51008"],"musicbrainz_discid": ["Oe4Aefz2EmmDP0_tYQNNNK5rzaU-"],"musicbrainz_recordingid": ["3e747efe-290d-4473-b2b7-7278a058233e"],"musicbrainz_releasegroupid": ["0555b77d-e1d9-32da-9e30-9573f0f6c291"],"musicbrainz_releasetrackid": ["54b646ff-6362-3c30-95d5-aebdd969d7f7"],"originaldate": ["1992-10-27"],"releasecountry": ["US"],"releasestatus": ["official"],"releasetype": ["album", "compilation"],"script": ["Latn"],"title": ["War Dance for Wooden Indians"],"totaldiscs": ["1"],"tracknumber": ["19"],"tracktotal": ["23"]},"version": {"highlevel": {"essentia": "2.1-beta5-dev","essentia_build_sha": "e74af04b57b164eed312abeef4963962215860f0","essentia_git_sha": "v2.1_beta4-499-g4013ebc","extractor": "music 2.0","gaia": "2.4.5","gaia_git_sha": "v2.4.4-44-g95f4851","models_essentia_git_sha": "v2.1_beta1"},"lowlevel": {"essentia": "2.1-beta2","essentia_build_sha": "70f2e5ece6736b2c40cc944ad0e695b16b925413","essentia_git_sha": "v2.1_beta2","extractor": "music 1.0"}}}}