{"highlevel": {"danceability": {"all": {"danceable": 0.999999880791,"not_danceable": 1.00000008274e-07},"probability": 0.999999880791,"value": "danceable"},"gender": {"all": {"female": 0.70296728611,"male": 0.297032743692},"probability": 0.70296728611,"value": "female"},"genre_dortmund": {"all": {"alternative": 5.70263054556e-08,"blues": 5.52550396549e-08,"electronic": 0.999979436398,"folkcountry": 4.41883003077e-06,"funksoulrnb": 3.51934716036e-07,"jazz": 1.39684216265e-05,"pop": 9.63348611549e-07,"raphiphop": 1.8712637484e-07,"rock": 5.46515195765e-07},"probability": 0.999979436398,"value": "electronic"},"genre_electronic": {"all": {"ambient": 0.0174407996237,"dnb": 0.00216723466292,"house": 0.0219674222171,"techno": 0.0142828077078,"trance": 0.944141745567},"probability": 0.944141745567,"value": "trance"},"genre_rosamerica": {"all": {"cla": 2.56399671343e-05,"dan": 0.963356912136,"hip": 0.00282241473906,"jaz": 5.33433812961e-05,"pop": 0.0287704933435,"rhy": 0.00410159770399,"roc": 0.000834853679407,"spe": 3.47412096744e-05},"probability": 0.963356912136,"value": "dan"},"genre_tzanetakis": {"all": {"blu": 0.0626613423228,"cla": 0.0348169617355,"cou": 0.104475811124,"dis": 0.0784321576357,"hip": 0.15692435205,"jaz": 0.313974827528,"met": 0.0448166541755,"pop": 0.0627359300852,"reg": 0.0627360641956,"roc": 0.0784258767962},"probability": 0.313974827528,"value": "jaz"},"ismir04_rhythm": {"all": {"ChaChaCha": 0.986141502857,"Jive": 0.00155059876852,"Quickstep": 0.000233897779253,"Rumba-American": 0.00756325898692,"Rumba-International": 0.000890531518962,"Rumba-Misc": 0.00079981260933,"Samba": 0.00119589117821,"Tango": 0.000581231492106,"VienneseWaltz": 0.000874315097462,"Waltz": 0.000168970247614},"probability": 0.986141502857,"value": "ChaChaCha"},"mood_acoustic": {"all": {"acoustic": 8.15684811362e-11,"not_acoustic": 1},"probability": 1,"value": "not_acoustic"},"mood_aggressive": {"all": {"aggressive": 3.19209370048e-08,"not_aggressive": 0.999999940395},"probability": 0.999999940395,"value": "not_aggressive"},"mood_electronic": {"all": {"electronic": 0.967322289944,"not_electronic": 0.0326776839793},"probability": 0.967322289944,"value": "electronic"},"mood_happy": {"all": {"happy": 0.869158565998,"not_happy": 0.1308414042},"probability": 0.869158565998,"value": "happy"},"mood_party": {"all": {"not_party": 0.21045166254,"party": 0.78954833746},"probability": 0.78954833746,"value": "party"},"mood_relaxed": {"all": {"not_relaxed": 0.190437406301,"relaxed": 0.809562623501},"probability": 0.809562623501,"value": "relaxed"},"mood_sad": {"all": {"not_sad": 0.83322262764,"sad": 0.166777342558},"probability": 0.83322262764,"value": "not_sad"},"moods_mirex": {"all": {"Cluster1": 0.0828144475818,"Cluster2": 0.0796178281307,"Cluster3": 0.128573969007,"Cluster4": 0.0896707847714,"Cluster5": 0.619322955608},"probability": 0.619322955608,"value": "Cluster5"},"timbre": {"all": {"bright": 0.296056300402,"dark": 0.703943669796},"probability": 0.703943669796,"value": "dark"},"tonal_atonal": {"all": {"atonal": 0.749454796314,"tonal": 0.250545203686},"probability": 0.749454796314,"value": "atonal"},"voice_instrumental": {"all": {"instrumental": 0.861230313778,"voice": 0.138769686222},"probability": 0.861230313778,"value": "instrumental"}},"metadata": {"audio_properties": {"analysis_sample_rate": 44100,"bit_rate": 192000,"equal_loudness": 0,"length": 302.524078369,"lossless": 0,"replay_gain": -13.8820343018,"sample_rate": 44100,"codec": "mp3","downmix": "mix","md5_encoded": "1c7e152346874fd1e5b5c9c93bff9eca"},"tags": {"file_name": "73832.mp3","album": ["blossom"],"albumartist": ["AGORIA"],"artist": ["AGORIA"],"date": ["2004"],"genre": ["Electronica"],"label": ["Different"],"length": ["302560"],"musicbrainz_recordingid": ["676f9fe4-2ff8-4f16-ad01-126363c44c97"],"title": ["Stereolove"],"tracknumber": ["3"]},"version": {"highlevel": {"essentia": "2.1-beta5-dev","essentia_build_sha": "e74af04b57b164eed312abeef4963962215860f0","essentia_git_sha": "v2.1_beta4-499-g4013ebc","extractor": "music 2.0","gaia": "2.4.5","gaia_git_sha": "v2.4.4-44-g95f4851","models_essentia_git_sha": "v2.1_beta1"},"lowlevel": {"essentia": "2.1-beta2","essentia_build_sha": "70f2e5ece6736b2c40cc944ad0e695b16b925413","essentia_git_sha": "v2.1_beta2","extractor": "music 1.0"}}}}